azure/mgmt/changeanalysis/__init__.py
azure/mgmt/changeanalysis/_azure_change_analysis_management_client.py
azure/mgmt/changeanalysis/_configuration.py
azure/mgmt/changeanalysis/_version.py
azure/mgmt/changeanalysis/aio/__init__.py
azure/mgmt/changeanalysis/aio/_azure_change_analysis_management_client.py
azure/mgmt/changeanalysis/aio/_configuration.py
azure/mgmt/changeanalysis/aio/operations/__init__.py
azure/mgmt/changeanalysis/aio/operations/_changes_operations.py
azure/mgmt/changeanalysis/aio/operations/_operations.py
azure/mgmt/changeanalysis/aio/operations/_resource_changes_operations.py
azure/mgmt/changeanalysis/models/__init__.py
azure/mgmt/changeanalysis/models/_azure_change_analysis_management_client_enums.py
azure/mgmt/changeanalysis/models/_models.py
azure/mgmt/changeanalysis/models/_models_py3.py
azure/mgmt/changeanalysis/operations/__init__.py
azure/mgmt/changeanalysis/operations/_changes_operations.py
azure/mgmt/changeanalysis/operations/_operations.py
azure/mgmt/changeanalysis/operations/_resource_changes_operations.py
azure_mgmt_changeanalysis-1.0.0.dist-info/METADATA
azure_mgmt_changeanalysis-1.0.0.dist-info/WHEEL
azure_mgmt_changeanalysis-1.0.0.dist-info/top_level.txt
azure_mgmt_changeanalysis-1.0.0.dist-info/RECORD
